{
  "sidebar": [
    {
      "type": "category",
      "label": "Wave",
      "collapsed": false,
      "items": [
        "index",
        "how-it-works",
        "build-custom-images",
        "docker-singularity",
        "architectures",
        "authentication",
        "augmentation",
        "container-freezes",
        "mirroring",
        "security"
      ]
    },
    "get-started",
    "seqera-containers.mdx",
    "nextflow",
    {
      "type": "category",
      "label": "Developer tools",
      "collapsed": true,
      "items": [
        "cli/index",
        "cli/reference",
        "api"
      ]
    },
    "faq"
  ]
}
